pytest_mark_no_py3/__init__.py
pytest_mark_no_py3/_bowler.py
pytest_mark_no_py3/add.py
pytest_mark_no_py3/plugin.py
pytest_mark_no_py3/remove.py
pytest_mark_no_py3-0.1.0.dist-info/LICENSE
pytest_mark_no_py3-0.1.0.dist-info/METADATA
pytest_mark_no_py3-0.1.0.dist-info/WHEEL
pytest_mark_no_py3-0.1.0.dist-info/entry_points.txt
pytest_mark_no_py3-0.1.0.dist-info/top_level.txt
pytest_mark_no_py3-0.1.0.dist-info/RECORD
