Metadata-Version: 2.1
Name: pytest-mark-no-py3
Version: 0.1.0
Summary: pytest plugin and bowler codemod to help migrate tests to Python 3
Home-page: https://github.com/GoodRx/pytest-mark-no-py3
License: MIT
Platform: UNKNOWN
Classifier: Intended Audience :: Developers
Classifier: Programming Language :: Python
Classifier: Programming Language :: Python :: 2.7
Classifier: Programming Language :: Python :: 3
Classifier: Programming Language :: Python :: 3.7
Classifier: License :: OSI Approved :: MIT License
Requires-Dist: pytest
Provides-Extra: bowler
Requires-Dist: bowler ; extra == 'bowler'
Requires-Dist: click ; extra == 'bowler'
Requires-Dist: attrs ; extra == 'bowler'
